{"imagePath":"1000439_tex.png","width":1024,"height":1024,"name":"1000439","SubTexture":[{"frameY":-7,"y":97,"frameWidth":306,"frameHeight":153,"width":265,"height":144,"name":"effects/heiyana7","frameX":-4,"x":723},{"frameY":-2,"y":377,"frameWidth":306,"frameHeight":153,"width":252,"height":134,"name":"effects/heiyana10","frameX":-13,"x":1},{"frameY":-8,"y":225,"frameWidth":306,"frameHeight":153,"width":254,"height":142,"name":"effects/heiyana6","frameX":-10,"x":269},{"frameY":-2,"y":100,"frameWidth":306,"frameHeight":153,"width":266,"height":136,"name":"effects/heiyana1","frameX":-7,"x":1},{"frameY":-12,"y":510,"frameWidth":306,"frameHeight":153,"width":230,"height":129,"name":"effects/heiyana2","frameX":-44,"x":255},{"frameY":-10,"y":369,"frameWidth":306,"frameHeight":153,"width":249,"height":139,"name":"effects/heiyana5","frameX":-17,"x":259},{"frameY":-14,"y":505,"frameWidth":306,"frameHeight":153,"width":233,"height":130,"name":"effects/heiyana3","frameX":-34,"x":754},{"frameY":-4,"y":374,"frameWidth":306,"frameHeight":153,"width":248,"height":129,"name":"effects/heiyana9","frameX":-20,"x":754},{"frameY":-12,"y":374,"frameWidth":306,"frameHeight":153,"width":242,"height":134,"name":"effects/heiyana4","frameX":-26,"x":510},{"frameY":-7,"y":238,"frameWidth":306,"frameHeight":153,"width":256,"height":137,"name":"effects/heiyana8","frameX":-3,"x":1},{"frameY":-94,"y":1,"frameWidth":613,"frameHeight":306,"width":421,"height":94,"name":"effects/aa1","frameX":-153,"x":413},{"frameY":-92,"y":1,"frameWidth":613,"frameHeight":306,"width":410,"height":97,"name":"effects/bb1","frameX":-157,"x":1},{"frameY":-25,"y":243,"frameWidth":306,"frameHeight":153,"width":197,"height":104,"name":"effects/heiyanb8","frameX":-104,"x":798},{"frameY":-20,"y":745,"frameWidth":306,"frameHeight":153,"width":183,"height":96,"name":"effects/heiyanb10","frameX":-114,"x":743},{"frameY":-19,"y":641,"frameWidth":306,"frameHeight":153,"width":176,"height":107,"name":"effects/heiyanb5","frameX":-123,"x":168},{"frameY":-22,"y":831,"frameWidth":306,"frameHeight":153,"width":168,"height":100,"name":"effects/heiyanb3","frameX":-135,"x":524},{"frameY":-21,"y":637,"frameWidth":306,"frameHeight":153,"width":185,"height":106,"name":"effects/heiyanb6","frameX":-115,"x":762},{"frameY":-24,"y":1,"frameWidth":306,"frameHeight":153,"width":186,"height":94,"name":"effects/heiyanb1","frameX":-108,"x":836},{"frameY":-21,"y":510,"frameWidth":306,"frameHeight":153,"width":186,"height":107,"name":"effects/heiyanb7","frameX":-109,"x":487},{"frameY":-22,"y":830,"frameWidth":306,"frameHeight":153,"width":176,"height":102,"name":"effects/heiyanb4","frameX":-128,"x":346},{"frameY":-28,"y":736,"frameWidth":306,"frameHeight":153,"width":200,"height":92,"name":"effects/heiyanb2","frameX":-103,"x":346},{"frameY":-22,"y":869,"frameWidth":306,"frameHeight":153,"width":177,"height":101,"name":"effects/heiyanb9","frameX":-120,"x":1},{"frameY":-36,"y":843,"frameWidth":416,"frameHeight":208,"width":104,"height":109,"name":"effects/diana5","frameX":-154,"x":811},{"frameY":-77,"y":934,"frameWidth":416,"frameHeight":208,"width":49,"height":43,"name":"effects/diana14","frameX":-100,"x":466},{"frameY":-63,"y":637,"frameWidth":416,"frameHeight":208,"width":273,"height":97,"name":"effects/diana13","frameX":-100,"x":487},{"frameY":-64,"y":934,"frameWidth":416,"frameHeight":208,"width":284,"height":59,"name":"effects/diana9","frameX":-124,"x":180},{"frameY":-27,"y":762,"frameWidth":416,"frameHeight":208,"width":160,"height":89,"name":"effects/diana16","frameX":-92,"x":1},{"frameY":-67,"y":972,"frameWidth":416,"frameHeight":208,"width":143,"height":44,"name":"effects/diana4","frameX":-247,"x":1},{"frameY":-58,"y":843,"frameWidth":416,"frameHeight":208,"width":115,"height":103,"name":"effects/diana12","frameX":-142,"x":694},{"frameY":-27,"y":933,"frameWidth":416,"frameHeight":208,"width":154,"height":89,"name":"effects/diana17","frameX":-92,"x":524},{"frameY":-93,"y":869,"frameWidth":416,"frameHeight":208,"width":148,"height":63,"name":"effects/diana20","frameX":-98,"x":180},{"frameY":-27,"y":243,"frameWidth":416,"frameHeight":208,"width":271,"height":129,"name":"effects/diana15","frameX":-93,"x":525},{"frameY":-52,"y":736,"frameWidth":416,"frameHeight":208,"width":193,"height":93,"name":"effects/diana7","frameX":-191,"x":548},{"frameY":-67,"y":641,"frameWidth":416,"frameHeight":208,"width":101,"height":86,"name":"effects/diana1","frameX":-139,"x":346},{"frameY":-36,"y":97,"frameWidth":416,"frameHeight":208,"width":308,"height":126,"name":"effects/diana11","frameX":-100,"x":413},{"frameY":-41,"y":750,"frameWidth":416,"frameHeight":208,"width":161,"height":117,"name":"effects/diana19","frameX":-93,"x":168},{"frameY":-73,"y":745,"frameWidth":416,"frameHeight":208,"width":72,"height":79,"name":"effects/diana3","frameX":-144,"x":928},{"frameY":-35,"y":513,"frameWidth":416,"frameHeight":208,"width":244,"height":113,"name":"effects/diana6","frameX":-165,"x":1},{"frameY":-75,"y":843,"frameWidth":416,"frameHeight":208,"width":79,"height":79,"name":"effects/diana2","frameX":-145,"x":917},{"frameY":-66,"y":100,"frameWidth":416,"frameHeight":208,"width":142,"height":96,"name":"effects/diana10","frameX":-103,"x":269},{"frameY":-28,"y":628,"frameWidth":416,"frameHeight":208,"width":165,"height":132,"name":"effects/diana18","frameX":-92,"x":1}]}