{"width":507,"imagePath":"403020102_tex.png","height":361,"name":"403020102","SubTexture":[{"width":64,"y":1,"height":64,"name":"effects/eff_glow_01","x":431},{"width":256,"y":1,"height":256,"name":"effects/eff_kuosan_q_01","x":1},{"width":170,"y":1,"height":170,"name":"effects/eff_baodian_d","x":259},{"width":100,"y":259,"height":100,"name":"effects/eff_baodian_e","x":1},{"width":128,"y":259,"height":64,"name":"effects/eff_shexian_a","x":103},{"width":134,"y":173,"height":117,"name":"effects/eff_ci_a","x":259},{"width":107,"y":173,"height":131,"name":"effects/eff_ci_b","x":395},{"y":292,"frameX":-12,"frameHeight":32,"frameY":-5,"width":104,"frameWidth":128,"height":21,"name":"effects/eff_baodian_b","x":233},{"width":36,"y":105,"height":36,"name":"effects/eff_lizi1","x":431},{"width":36,"y":67,"height":36,"name":"effects/eff_lizi2","x":431},{"width":36,"y":67,"height":36,"name":"effects/eff_lizi3","x":469}]}