{"width":1024,"SubTexture":[{"width":325,"y":709,"height":62,"name":"yinying","x":286},{"width":534,"y":2,"height":192,"name":"guancai2","x":2},{"width":42,"y":899,"height":87,"name":"st__56","x":300},{"width":90,"y":575,"height":101,"name":"st__55","x":927},{"width":104,"y":820,"height":66,"name":"st__54","x":2},{"width":555,"y":196,"height":147,"name":"guancai1","x":2},{"width":123,"y":549,"height":184,"name":"st__52","x":2},{"width":133,"y":2,"height":260,"name":"pd1","x":799},{"width":194,"y":600,"height":107,"name":"st__50","x":424},{"width":167,"y":345,"height":185,"name":"st__49","x":359},{"width":187,"y":345,"height":179,"name":"st__48","x":170},{"width":67,"y":837,"height":90,"name":"st__47","x":954},{"frameX":-1,"frameHeight":74,"y":888,"frameY":-1,"frameWidth":85,"width":83,"height":72,"name":"st__46","x":2},{"frameX":-1,"frameHeight":88,"y":837,"frameY":-1,"frameWidth":80,"width":78,"height":86,"name":"st__45","x":874},{"frameX":-1,"frameHeight":84,"y":892,"frameY":-1,"frameWidth":56,"width":54,"height":82,"name":"st__44","x":786},{"frameX":-1,"frameHeight":165,"y":600,"frameY":-1,"frameWidth":127,"width":125,"height":163,"name":"st__43","x":620},{"frameX":-1,"frameHeight":194,"y":264,"frameY":-1,"frameWidth":125,"width":123,"height":192,"name":"st__42","x":859},{"width":77,"y":111,"height":102,"name":"st__41","x":934},{"frameX":-1,"frameHeight":121,"y":704,"frameY":-1,"frameWidth":160,"width":158,"height":119,"name":"st__40","x":747},{"frameX":-1,"frameHeight":130,"y":765,"frameY":-1,"frameWidth":97,"width":95,"height":128,"name":"st__39","x":613},{"width":114,"y":526,"height":217,"name":"st__38","x":170},{"width":162,"y":825,"height":65,"name":"st__37","x":710},{"width":136,"y":532,"height":168,"name":"st__33","x":286},{"frameX":-1,"frameHeight":129,"y":575,"frameY":-1,"frameWidth":174,"width":172,"height":127,"name":"st__30","x":753},{"width":157,"y":735,"height":83,"name":"st__29","x":2},{"width":238,"y":2,"height":278,"name":"st__28","x":559},{"frameX":-1,"frameHeight":42,"y":215,"frameY":-1,"frameWidth":42,"width":40,"height":40,"name":"st__27","x":934},{"width":120,"y":773,"height":96,"name":"st__26","x":385},{"width":122,"y":745,"height":103,"name":"st__25","x":161},{"width":52,"y":920,"height":69,"name":"st__21","x":586},{"width":69,"y":850,"height":92,"name":"st__20","x":181},{"width":83,"y":2,"height":107,"name":"st__19","x":934},{"width":100,"y":704,"height":131,"name":"st__18","x":907},{"width":117,"y":871,"height":55,"name":"st__24","x":385},{"width":298,"y":282,"height":177,"name":"st__23","x":559},{"width":80,"y":872,"height":79,"name":"st__22","x":504},{"frameX":-1,"frameHeight":25,"y":895,"frameY":-1,"frameWidth":200,"width":198,"height":23,"name":"st__17","x":586},{"frameX":-1,"frameHeight":57,"y":532,"frameY":-1,"frameWidth":56,"width":54,"height":55,"name":"st__16","x":424},{"frameX":-1,"frameHeight":126,"y":773,"frameY":-1,"frameWidth":100,"width":98,"height":124,"name":"st__15","x":285},{"width":24,"y":345,"height":54,"name":"st__14","x":528},{"frameX":-1,"frameHeight":204,"y":345,"frameY":-1,"frameWidth":168,"width":166,"height":202,"name":"st__13","x":2},{"width":26,"y":280,"height":72,"name":"st__12","x":984},{"width":19,"y":2,"height":80,"name":"huzi1","x":538},{"width":42,"y":920,"height":77,"name":"st__10","x":687},{"width":45,"y":920,"height":74,"name":"st__9","x":640},{"width":33,"y":215,"height":63,"name":"st__8","x":984},{"width":46,"y":899,"height":82,"name":"st__7","x":252},{"width":53,"y":920,"height":28,"name":"st__6","x":731},{"width":40,"y":532,"height":19,"name":"st__5","x":480},{"width":31,"y":354,"height":19,"name":"st__4","x":984},{"width":84,"y":678,"height":21,"name":"ym","x":927},{"width":46,"y":264,"height":12,"name":"zm","x":799},{"width":243,"y":461,"height":112,"name":"st__36","x":753},{"width":73,"y":773,"height":97,"name":"st__34","x":507},{"frameX":-1,"frameHeight":96,"y":850,"frameY":-1,"frameWidth":73,"width":71,"height":94,"name":"st__32","x":108},{"width":223,"y":461,"height":137,"name":"st__31","x":528}],"height":1000,"name":"404080","imagePath":"404080_tex.png"}