{"width":507,"SubTexture":[{"frameWidth":116,"y":207,"frameHeight":116,"width":99,"frameX":-11,"height":99,"name":"effects/eff_ui_01","frameY":-8,"x":203},{"frameWidth":116,"y":308,"frameHeight":116,"width":100,"frameX":-10,"height":97,"name":"effects/eff_ui_04","frameY":-9,"x":201},{"frameWidth":116,"y":1,"frameHeight":116,"width":99,"frameX":-11,"height":101,"name":"effects/eff_ui_07","frameY":-7,"x":224},{"frameWidth":116,"y":172,"frameHeight":116,"width":99,"frameX":-11,"height":99,"name":"effects/eff_ui_00","frameY":-8,"x":102},{"frameWidth":116,"y":172,"frameHeight":116,"width":99,"frameX":-11,"height":101,"name":"effects/eff_ui_09","frameY":-7,"x":1},{"frameWidth":116,"y":207,"frameHeight":116,"width":99,"frameX":-11,"height":99,"name":"effects/eff_ui_06","frameY":-8,"x":304},{"frameWidth":116,"y":104,"frameHeight":116,"width":99,"frameX":-11,"height":101,"name":"effects/eff_ui_08","frameY":-7,"x":224},{"frameWidth":116,"y":1,"frameHeight":116,"width":99,"frameX":-11,"height":101,"name":"effects/eff_ui_14","frameY":-7,"x":325},{"frameWidth":116,"y":407,"frameHeight":116,"width":99,"frameX":-11,"height":95,"name":"effects/eff_ui_03","frameY":-10,"x":197},{"frameWidth":116,"y":307,"frameHeight":116,"width":97,"frameX":-12,"height":101,"name":"effects/eff_ui_13","frameY":-7,"x":405},{"frameWidth":116,"y":104,"frameHeight":116,"width":99,"frameX":-11,"height":101,"name":"effects/eff_ui_15","frameY":-7,"x":325},{"frameWidth":116,"y":308,"frameHeight":116,"width":99,"frameX":-11,"height":97,"name":"effects/eff_ui_02","frameY":-9,"x":303},{"frameWidth":116,"y":376,"frameHeight":116,"width":95,"frameX":-13,"height":101,"name":"effects/eff_ui_11","frameY":-7,"x":100},{"frameWidth":116,"y":275,"frameHeight":116,"width":97,"frameX":-12,"height":101,"name":"effects/eff_ui_12","frameY":-7,"x":1},{"frameWidth":116,"y":273,"frameHeight":116,"width":97,"frameX":-12,"height":101,"name":"effects/eff_ui_10","frameY":-7,"x":102},{"frameWidth":116,"y":207,"frameHeight":116,"width":100,"frameX":-10,"height":98,"name":"effects/eff_ui_05","frameY":-8,"x":405},{"frameWidth":256,"y":1,"frameHeight":256,"width":221,"frameX":-18,"height":169,"name":"effects/eff_glow_03","frameY":-44,"x":1}],"height":504,"name":"1000017","imagePath":"1000017_tex.png"}