{"width":1024,"SubTexture":[{"frameX":-11,"frameHeight":128,"y":840,"frameY":-11,"frameWidth":128,"width":106,"height":106,"name":"jinzhizhaomu/glow_01","x":637},{"width":37,"y":1,"height":53,"name":"jinzhizhaomu/shitou9","x":913},{"width":95,"y":607,"height":124,"name":"jinzhizhaomu/shitou8","x":540},{"width":98,"y":840,"height":97,"name":"jinzhizhaomu/shitou7","x":745},{"width":27,"y":749,"height":25,"name":"jinzhizhaomu/shitou6","x":451},{"width":129,"y":792,"height":146,"name":"jinzhizhaomu/shitou5","x":432},{"width":111,"y":733,"height":105,"name":"jinzhizhaomu/shitou4","x":563},{"width":83,"y":940,"height":69,"name":"jinzhizhaomu/shitou3","x":432},{"width":29,"y":917,"height":28,"name":"jinzhizhaomu/shitou2","x":592},{"width":144,"y":607,"height":183,"name":"jinzhizhaomu/shitou1","x":305},{"width":75,"y":939,"height":84,"name":"jinzhizhaomu/fuwen8","x":745},{"width":42,"y":939,"height":67,"name":"jinzhizhaomu/fuwen7","x":822},{"width":59,"y":948,"height":60,"name":"jinzhizhaomu/fuwen6","x":592},{"frameX":0,"frameHeight":56,"y":948,"frameY":0,"frameWidth":65,"width":65,"height":49,"name":"jinzhizhaomu/fuwen5","x":653},{"width":64,"y":840,"height":75,"name":"jinzhizhaomu/fuwen4","x":563},{"frameX":0,"frameHeight":48,"y":961,"frameY":0,"frameWidth":51,"width":51,"height":46,"name":"jinzhizhaomu/fuwen3","x":377},{"frameX":0,"frameHeight":71,"y":940,"frameY":-1,"frameWidth":73,"width":73,"height":70,"name":"jinzhizhaomu/fuwen2","x":517},{"frameX":-1,"frameHeight":61,"y":961,"frameY":0,"frameWidth":71,"width":70,"height":60,"name":"jinzhizhaomu/fuwen1","x":305},{"width":150,"y":1,"height":200,"name":"jinzhizhaomu/jinghai_05","x":305},{"width":150,"y":203,"height":200,"name":"jinzhizhaomu/jinghai_03","x":1},{"width":150,"y":809,"height":200,"name":"jinzhizhaomu/jinghai_10","x":153},{"width":150,"y":1,"height":200,"name":"jinzhizhaomu/jinghai_01","x":1},{"width":150,"y":203,"height":200,"name":"jinzhizhaomu/jinghai_04","x":153},{"width":150,"y":405,"height":200,"name":"jinzhizhaomu/jinghai_07","x":305},{"width":150,"y":1,"height":200,"name":"jinzhizhaomu/jinghai_11","x":609},{"width":150,"y":1,"height":200,"name":"jinzhizhaomu/jinghai_12","x":153},{"width":150,"y":607,"height":200,"name":"jinzhizhaomu/jinghai_00","x":153},{"width":150,"y":405,"height":200,"name":"jinzhizhaomu/jinghai_09","x":153},{"width":150,"y":809,"height":200,"name":"jinzhizhaomu/jinghai_02","x":1},{"width":150,"y":607,"height":200,"name":"jinzhizhaomu/jinghai_08","x":1},{"width":150,"y":203,"height":200,"name":"jinzhizhaomu/jinghai_06","x":305},{"width":150,"y":405,"height":200,"name":"jinzhizhaomu/jinghai_14","x":1},{"width":150,"y":1,"height":200,"name":"jinzhizhaomu/jinghai_15","x":761},{"width":150,"y":1,"height":200,"name":"jinzhizhaomu/jinghai_13","x":457},{"width":125,"y":792,"height":167,"name":"jinzhizhaomu/jinghai","x":305},{"width":87,"y":607,"height":140,"name":"jinzhizhaomu/jinghai_a","x":451}],"height":1024,"name":"1000064","imagePath":"1000064_tex.png"}