{"1":{"kf_cross_duel_open_day":{"val":23},"kf_cross_duel_signup_dura_day":{"val":2},"kf_cross_duel_junior_dura_day":{"val":7},"kf_cross_duel_group_dura_day":{"val":1},"kf_cross_duel_final_dura_day":{"val":1},"kf_cross_duel_settle_dura_day":{"val":2},"kf_cross_duel_junior_open_hour":{"val":"{8,21}"},"kf_cross_duel_junior_settle_days":{"val":"[2,4,6,7]"},"kf_cross_duel_junior_settle_hour":{"val":21},"kf_cross_duel_junior_room_tier1_num":{"val":200},"kf_cross_duel_junior_room_tier2_num":{"val":50},"kf_cross_duel_junior_room_tier1_player_limit":{"val":50},"kf_cross_duel_junior_room_tier2_player_limit":{"val":50},"kf_cross_duel_junior_room_evolve_top_num":{"val":5},"kf_cross_duel_group_open_hour":{"val":20},"kf_cross_duel_group_round_fight_minus":{"val":10},"kf_cross_duel_group_round_ready_minus":{"val":5},"kf_cross_duel_base_score":{"val":1000},"kf_cross_duel_max_round":{"val":10},"kf_cross_duel_refresh_enemy_cd":{"val":1},"kf_cross_duel_item_buy_cost":{"val":20},"kf_cross_duel_junior_enemy_num":{"val":5},"kf_cross_duel_junior_free_challenge_times":{"val":10},"kf_cross_duel_guess_open_time":{"val":"{8,20}"},"kf_cross_duel_log_num":{"val":20},"kf_cross_duel_rank_num":{"val":100},"kf_cross_duel_worship_gain":{"val":[{"type":"gain","label":"item","base_id":2,"bind":1,"num":50}]},"kf_cross_duel_worship_num":{"val":4},"kf_cross_duel_unit_list":{"val":"[1500001,1500002,1500002,1500003,1500003,1500004,1500004,1500005,1500005,1500006,1500006,1500007,1500007,1500008,1500008,1500009,1500009,1500010,1500010,1500011,1500011,1500012,1500012,1500013,1500013,1500014,1500014,1500015,1500015,1500016,1500016,1500017,1500017,1500018,1500018,1500019,1500019,1500020,1500020,1500021,1500021,1500022,1500022,1500023,1500023,1500024,1500024,1500025,1500025,1500026,1500026,1500027,1500027,1500028,1500028,1500029,1500029,1500030,1500030,1500031,1500031,1500032,1500032,1500033,1500033,1500034,1500034,1500035,1500035,1500036,1500036,1500037,1500037,1500038,1500038,1500039,1500039,1500040,1500040]"},"kf_cross_duel_battle_award_limit":{"val":20},"kf_cross_duel_battle_item":{"val":[{"type":"loss","label":"item","base_id":1000111,"bind":1,"num":1}]},"kf_cross_duel_battle_item_buy":{"val":10},"kf_cross_duel_rise_reward":{"val":[{"type":"gain","label":"item","base_id":90001014,"bind":1,"num":2},{"type":"gain","label":"item","base_id":80000008,"bind":1,"num":10}]},"kf_cross_duel_combat_scene_id":{"val":108},"kf_cross_duel_lower_mail":{"val":3501},"kf_cross_duel_middle_mail":{"val":3502},"kf_cross_duel_senior_mail":{"val":3503},"kf_cross_duel_rise_mail":{"val":3504},"kf_cross_duel_show_title":{"val":3100301},"kf_cross_duel_upper_mail":{"val":3505},"kf_cross_duel_bet_ground_mail":{"val":3508},"kf_cross_duel_bet_last_mail":{"val":3509},"kf_cross_duel_high_battle_free_time":{"val":10},"kf_cross_duel_high_battle_pay_id":{"val":701004},"kf_cross_duel_normal_battle_pay_id":{"val":701003},"kf_cross_duel_open_flag":{"val":1}},"2":{"1":{"id":1,"low":1,"up":1,"award":[{"type":"gain","label":"item","base_id":3100301,"bind":1,"num":1},{"type":"gain","label":"item","base_id":120,"bind":1,"num":15000},{"type":"gain","label":"item","base_id":80000008,"bind":1,"num":30},{"type":"gain","label":"item","base_id":2,"bind":1,"num":2000}],"designation_id":3100301},"2":{"id":2,"low":2,"up":2,"award":[{"type":"gain","label":"item","base_id":3100302,"bind":1,"num":1},{"type":"gain","label":"item","base_id":120,"bind":1,"num":13000},{"type":"gain","label":"item","base_id":80000008,"bind":1,"num":25},{"type":"gain","label":"item","base_id":2,"bind":1,"num":1800}],"designation_id":3100302},"3":{"id":3,"low":3,"up":3,"award":[{"type":"gain","label":"item","base_id":3100303,"bind":1,"num":1},{"type":"gain","label":"item","base_id":120,"bind":1,"num":11000},{"type":"gain","label":"item","base_id":80000008,"bind":1,"num":20},{"type":"gain","label":"item","base_id":2,"bind":1,"num":1600}],"designation_id":3100303},"4":{"id":4,"low":4,"up":4,"award":[{"type":"gain","label":"item","base_id":3100304,"bind":1,"num":1},{"type":"gain","label":"item","base_id":120,"bind":1,"num":9000},{"type":"gain","label":"item","base_id":80000008,"bind":1,"num":18},{"type":"gain","label":"item","base_id":2,"bind":1,"num":1400}],"designation_id":3100304},"5":{"id":5,"low":5,"up":8,"award":[{"type":"gain","label":"item","base_id":120,"bind":1,"num":7000},{"type":"gain","label":"item","base_id":80000008,"bind":1,"num":16},{"type":"gain","label":"item","base_id":2,"bind":1,"num":1200}],"designation_id":""},"6":{"id":6,"low":9,"up":16,"award":[{"type":"gain","label":"item","base_id":120,"bind":1,"num":5000},{"type":"gain","label":"item","base_id":80000008,"bind":1,"num":14},{"type":"gain","label":"item","base_id":2,"bind":1,"num":1000}],"designation_id":""},"7":{"id":7,"low":17,"up":32,"award":[{"type":"gain","label":"item","base_id":120,"bind":1,"num":4000},{"type":"gain","label":"item","base_id":80000008,"bind":1,"num":12},{"type":"gain","label":"item","base_id":2,"bind":1,"num":800}],"designation_id":""},"8":{"id":8,"low":33,"up":64,"award":[{"type":"gain","label":"item","base_id":120,"bind":1,"num":3000},{"type":"gain","label":"item","base_id":80000008,"bind":1,"num":10},{"type":"gain","label":"item","base_id":2,"bind":1,"num":600}],"designation_id":""},"9":{"id":9,"low":65,"up":128,"award":[{"type":"gain","label":"item","base_id":120,"bind":1,"num":2000},{"type":"gain","label":"item","base_id":80000008,"bind":1,"num":8},{"type":"gain","label":"item","base_id":2,"bind":1,"num":400}],"designation_id":""}},"3":{"1":{"room":1,"rank":"[1,1]","award":[{"type":"gain","label":"item","base_id":120,"bind":1,"num":3000},{"type":"gain","label":"item","base_id":1000050,"bind":1,"num":300}]},"2":{"room":1,"rank":"[2,2]","award":[{"type":"gain","label":"item","base_id":120,"bind":1,"num":2500},{"type":"gain","label":"item","base_id":1000050,"bind":1,"num":250}]},"3":{"room":1,"rank":"[3,3]","award":[{"type":"gain","label":"item","base_id":120,"bind":1,"num":2000},{"type":"gain","label":"item","base_id":1000050,"bind":1,"num":200}]},"4":{"room":1,"rank":"[4,10]","award":[{"type":"gain","label":"item","base_id":120,"bind":1,"num":1500},{"type":"gain","label":"item","base_id":1000050,"bind":1,"num":150}]},"5":{"room":1,"rank":"[11,20]","award":[{"type":"gain","label":"item","base_id":120,"bind":1,"num":1000},{"type":"gain","label":"item","base_id":1000050,"bind":1,"num":100}]},"6":{"room":1,"rank":"[21,50]","award":[{"type":"gain","label":"item","base_id":120,"bind":1,"num":500},{"type":"gain","label":"item","base_id":1000050,"bind":1,"num":50}]},"7":{"room":2,"rank":"[1,1]","award":[{"type":"gain","label":"item","base_id":120,"bind":1,"num":4500},{"type":"gain","label":"item","base_id":1000050,"bind":1,"num":450}]},"8":{"room":2,"rank":"[2,2]","award":[{"type":"gain","label":"item","base_id":120,"bind":1,"num":4000},{"type":"gain","label":"item","base_id":1000050,"bind":1,"num":400}]},"9":{"room":2,"rank":"[3,3]","award":[{"type":"gain","label":"item","base_id":120,"bind":1,"num":3500},{"type":"gain","label":"item","base_id":1000050,"bind":1,"num":350}]},"10":{"room":2,"rank":"[4,10]","award":[{"type":"gain","label":"item","base_id":120,"bind":1,"num":3000},{"type":"gain","label":"item","base_id":1000050,"bind":1,"num":300}]},"11":{"room":2,"rank":"[11,20]","award":[{"type":"gain","label":"item","base_id":120,"bind":1,"num":2000},{"type":"gain","label":"item","base_id":1000050,"bind":1,"num":200}]},"12":{"room":2,"rank":"[21,50]","award":[{"type":"gain","label":"item","base_id":120,"bind":1,"num":1000},{"type":"gain","label":"item","base_id":1000050,"bind":1,"num":100}]},"13":{"room":3,"rank":"[1,1]","award":[{"type":"gain","label":"item","base_id":120,"bind":1,"num":8000},{"type":"gain","label":"item","base_id":1000050,"bind":1,"num":800}]},"14":{"room":3,"rank":"[2,2]","award":[{"type":"gain","label":"item","base_id":120,"bind":1,"num":7500},{"type":"gain","label":"item","base_id":1000050,"bind":1,"num":750}]},"15":{"room":3,"rank":"[3,3]","award":[{"type":"gain","label":"item","base_id":120,"bind":1,"num":7000},{"type":"gain","label":"item","base_id":1000050,"bind":1,"num":700}]},"16":{"room":3,"rank":"[4,10]","award":[{"type":"gain","label":"item","base_id":120,"bind":1,"num":6500},{"type":"gain","label":"item","base_id":1000050,"bind":1,"num":650}]},"17":{"room":3,"rank":"[11,20]","award":[{"type":"gain","label":"item","base_id":120,"bind":1,"num":6000},{"type":"gain","label":"item","base_id":1000050,"bind":1,"num":600}]},"18":{"room":3,"rank":"[21,50]","award":[{"type":"gain","label":"item","base_id":120,"bind":1,"num":5000},{"type":"gain","label":"item","base_id":1000050,"bind":1,"num":500}]},"19":{"room":3,"rank":"[51,100]","award":[{"type":"gain","label":"item","base_id":120,"bind":1,"num":4000},{"type":"gain","label":"item","base_id":1000050,"bind":1,"num":400}]},"20":{"room":3,"rank":"[101,200]","award":[{"type":"gain","label":"item","base_id":120,"bind":1,"num":3000},{"type":"gain","label":"item","base_id":1000050,"bind":1,"num":300}]},"21":{"room":3,"rank":"[201,300]","award":[{"type":"gain","label":"item","base_id":120,"bind":1,"num":2000},{"type":"gain","label":"item","base_id":1000050,"bind":1,"num":200}]},"22":{"room":3,"rank":"[301,9999]","award":[{"type":"gain","label":"item","base_id":120,"bind":1,"num":1500},{"type":"gain","label":"item","base_id":1000050,"bind":1,"num":150}]}},"4":{"1":{"room":1,"point_gap":"","win_point":25},"2":{"room":1,"point_gap":"","win_point":22},"3":{"room":1,"point_gap":"","win_point":20},"4":{"room":1,"point_gap":"","win_point":18},"5":{"room":1,"point_gap":"","win_point":15},"6":{"room":1,"point_gap":"","win_point":25},"7":{"room":1,"point_gap":"","win_point":22},"8":{"room":1,"point_gap":"","win_point":20},"9":{"room":1,"point_gap":"","win_point":18},"10":{"room":1,"point_gap":"","win_point":15},"11":{"room":1,"point_gap":"","win_point":25},"12":{"room":1,"point_gap":"","win_point":22},"13":{"room":1,"point_gap":"","win_point":20},"14":{"room":1,"point_gap":"","win_point":18},"15":{"room":1,"point_gap":"","win_point":15},"16":{"room":1,"point_gap":"","win_point":25},"17":{"room":1,"point_gap":"","win_point":22},"18":{"room":1,"point_gap":"","win_point":20},"19":{"room":1,"point_gap":"","win_point":18},"20":{"room":1,"point_gap":"","win_point":15},"21":{"room":2,"point_gap":"","win_point":25},"22":{"room":2,"point_gap":"","win_point":22},"23":{"room":2,"point_gap":"","win_point":20},"24":{"room":2,"point_gap":"","win_point":18},"25":{"room":2,"point_gap":"","win_point":15},"26":{"room":2,"point_gap":"","win_point":25},"27":{"room":2,"point_gap":"","win_point":22},"28":{"room":2,"point_gap":"","win_point":20},"29":{"room":2,"point_gap":"","win_point":18},"30":{"room":2,"point_gap":"","win_point":15},"31":{"room":2,"point_gap":"","win_point":25},"32":{"room":2,"point_gap":"","win_point":22},"33":{"room":2,"point_gap":"","win_point":20},"34":{"room":2,"point_gap":"","win_point":18},"35":{"room":2,"point_gap":"","win_point":15},"36":{"room":2,"point_gap":"","win_point":25},"37":{"room":2,"point_gap":"","win_point":22},"38":{"room":2,"point_gap":"","win_point":20},"39":{"room":2,"point_gap":"","win_point":18},"40":{"room":2,"point_gap":"","win_point":15},"41":{"room":3,"point_gap":"","win_point":25},"42":{"room":3,"point_gap":"","win_point":22},"43":{"room":3,"point_gap":"","win_point":20},"44":{"room":3,"point_gap":"","win_point":18},"45":{"room":3,"point_gap":"","win_point":15},"46":{"room":3,"point_gap":"","win_point":25},"47":{"room":3,"point_gap":"","win_point":22},"48":{"room":3,"point_gap":"","win_point":20},"49":{"room":3,"point_gap":"","win_point":18},"50":{"room":3,"point_gap":"","win_point":15},"51":{"room":3,"point_gap":"","win_point":25},"52":{"room":3,"point_gap":"","win_point":22},"53":{"room":3,"point_gap":"","win_point":20},"54":{"room":3,"point_gap":"","win_point":18},"55":{"room":3,"point_gap":"","win_point":15},"56":{"room":3,"point_gap":"","win_point":25},"57":{"room":3,"point_gap":"","win_point":22},"58":{"room":3,"point_gap":"","win_point":20},"59":{"room":3,"point_gap":"","win_point":18},"60":{"room":3,"point_gap":"","win_point":15},"61":{"room":3,"point_gap":"","win_point":25},"62":{"room":3,"point_gap":"","win_point":22},"63":{"room":3,"point_gap":"","win_point":20},"64":{"room":3,"point_gap":"","win_point":18},"65":{"room":3,"point_gap":"","win_point":15},"66":{"room":3,"point_gap":"","win_point":25},"67":{"room":3,"point_gap":"","win_point":22},"68":{"room":3,"point_gap":"","win_point":20},"69":{"room":3,"point_gap":"","win_point":18},"70":{"room":3,"point_gap":"","win_point":15},"71":{"room":3,"point_gap":"","win_point":25},"72":{"room":3,"point_gap":"","win_point":22},"73":{"room":3,"point_gap":"","win_point":20},"74":{"room":3,"point_gap":"","win_point":18},"75":{"room":3,"point_gap":"","win_point":15},"76":{"room":3,"point_gap":"","win_point":25},"77":{"room":3,"point_gap":"","win_point":22},"78":{"room":3,"point_gap":"","win_point":20},"79":{"room":3,"point_gap":"","win_point":18},"80":{"room":3,"point_gap":"","win_point":15},"81":{"room":3,"point_gap":"","win_point":25},"82":{"room":3,"point_gap":"","win_point":22},"83":{"room":3,"point_gap":"","win_point":20},"84":{"room":3,"point_gap":"","win_point":18},"85":{"room":3,"point_gap":"","win_point":15},"86":{"room":3,"point_gap":"","win_point":25},"87":{"room":3,"point_gap":"","win_point":22},"88":{"room":3,"point_gap":"","win_point":20},"89":{"room":3,"point_gap":"","win_point":18},"90":{"room":3,"point_gap":"","win_point":15}},"5":{"1":{"stage":1,"val":0,"reward":[{"type":"gain","label":"item","base_id":120,"bind":1,"num":200},{"type":"gain","label":"item","base_id":2,"bind":1,"num":25}]},"2":{"stage":1,"val":1,"reward":[{"type":"gain","label":"item","base_id":120,"bind":1,"num":400},{"type":"gain","label":"item","base_id":2,"bind":1,"num":50}]},"3":{"stage":1,"val":2,"reward":[{"type":"gain","label":"item","base_id":120,"bind":1,"num":600},{"type":"gain","label":"item","base_id":2,"bind":1,"num":75}]},"4":{"stage":1,"val":3,"reward":[{"type":"gain","label":"item","base_id":120,"bind":1,"num":800},{"type":"gain","label":"item","base_id":2,"bind":1,"num":100}]},"5":{"stage":1,"val":4,"reward":[{"type":"gain","label":"item","base_id":120,"bind":1,"num":1000},{"type":"gain","label":"item","base_id":2,"bind":1,"num":150}]},"6":{"stage":2,"val":0,"reward":[{"type":"gain","label":"item","base_id":120,"bind":1,"num":200},{"type":"gain","label":"item","base_id":2,"bind":1,"num":25}]},"7":{"stage":2,"val":1,"reward":[{"type":"gain","label":"item","base_id":120,"bind":1,"num":400},{"type":"gain","label":"item","base_id":2,"bind":1,"num":50}]},"8":{"stage":2,"val":2,"reward":[{"type":"gain","label":"item","base_id":120,"bind":1,"num":600},{"type":"gain","label":"item","base_id":2,"bind":1,"num":75}]},"9":{"stage":2,"val":3,"reward":[{"type":"gain","label":"item","base_id":120,"bind":1,"num":800},{"type":"gain","label":"item","base_id":2,"bind":1,"num":100}]},"10":{"stage":2,"val":4,"reward":[{"type":"gain","label":"item","base_id":120,"bind":1,"num":1000},{"type":"gain","label":"item","base_id":2,"bind":1,"num":150}]}},"6":{"1":{"day":1,"word":"Giai đoạn báo danh (Ngày 1)"},"2":{"day":2,"word":"Giai đoạn báo danh (Ngày 2)"},"3":{"day":3,"word":"Đấu Loại Ngày 1"},"4":{"day":4,"word":"Đấu Loại Ngày 2 (Tổng kết vòng 1)"},"5":{"day":5,"word":"Đấu Loại Ngày 3"},"6":{"day":6,"word":"Đấu Loại Ngày 4 (Tổng kết vòng 2)"},"7":{"day":7,"word":"Đấu Loại Ngày 5"},"8":{"day":8,"word":"Đấu Loại Ngày 6 (Tổng kết vòng 3)"},"9":{"day":9,"word":"Đấu Loại Ngày 6 (Tổng kết vòng cuối)"},"10":{"day":10,"word":"Chung Kết - Đấu Nhóm"},"11":{"day":11,"word":"Chung Kết - Đấu Chí Tôn"},"12":{"day":12,"word":"Mừng Quán Quân (Ngày 1)"},"13":{"day":13,"word":"Mừng Quán Quân (Ngày 2)"}}}