{"yszlinfo":{"1":{"term_id":1,"charge_id":1303,"gift_award":[{"type":"gain","label":"item","base_id":2,"bind":1,"num":1280},{"type":"gain","label":"item","base_id":20000011,"bind":1,"num":1},{"type":"gain","label":"item","base_id":4000004,"bind":1,"num":1}],"buy_preview":[{"type":"gain","label":"item","base_id":2,"bind":1,"num":1280},{"type":"gain","label":"item","base_id":1001122,"bind":1,"num":1},{"type":"gain","label":"item","base_id":20000011,"bind":1,"num":1},{"type":"gain","label":"item","base_id":4000004,"bind":1,"num":1}],"preview":[{"type":"gain","label":"item","base_id":4000010,"bind":1,"num":1},{"type":"gain","label":"item","base_id":4000011,"bind":1,"num":3},{"type":"gain","label":"item","base_id":4000009,"bind":1,"num":6},{"type":"gain","label":"item","base_id":4000004,"bind":1,"num":7},{"type":"gain","label":"item","base_id":4000012,"bind":1,"num":90}]},"2":{"term_id":2,"charge_id":1303,"gift_award":[{"type":"gain","label":"item","base_id":2,"bind":1,"num":1280},{"type":"gain","label":"item","base_id":20000011,"bind":1,"num":1},{"type":"gain","label":"item","base_id":4000004,"bind":1,"num":1}],"buy_preview":[{"type":"gain","label":"item","base_id":2,"bind":1,"num":1280},{"type":"gain","label":"item","base_id":1001122,"bind":1,"num":1},{"type":"gain","label":"item","base_id":20000011,"bind":1,"num":1},{"type":"gain","label":"item","base_id":4000004,"bind":1,"num":1}],"preview":[{"type":"gain","label":"item","base_id":4000010,"bind":1,"num":1},{"type":"gain","label":"item","base_id":4000011,"bind":1,"num":3},{"type":"gain","label":"item","base_id":4000009,"bind":1,"num":6},{"type":"gain","label":"item","base_id":4000004,"bind":1,"num":7},{"type":"gain","label":"item","base_id":4000012,"bind":1,"num":90}]},"3":{"term_id":3,"charge_id":1303,"gift_award":[{"type":"gain","label":"item","base_id":2,"bind":1,"num":1280},{"type":"gain","label":"item","base_id":20000011,"bind":1,"num":1},{"type":"gain","label":"item","base_id":4000004,"bind":1,"num":1}],"buy_preview":[{"type":"gain","label":"item","base_id":2,"bind":1,"num":1280},{"type":"gain","label":"item","base_id":1001122,"bind":1,"num":1},{"type":"gain","label":"item","base_id":20000011,"bind":1,"num":1},{"type":"gain","label":"item","base_id":4000004,"bind":1,"num":1}],"preview":[{"type":"gain","label":"item","base_id":4000010,"bind":1,"num":1},{"type":"gain","label":"item","base_id":4000011,"bind":1,"num":3},{"type":"gain","label":"item","base_id":4000009,"bind":1,"num":6},{"type":"gain","label":"item","base_id":4000004,"bind":1,"num":7},{"type":"gain","label":"item","base_id":4000012,"bind":1,"num":90}]}},"yszlreward":{"1":{"term_id":1,"num":1,"award":[{"type":"gain","label":"item","base_id":4000009,"bind":1,"num":1}],"award2":[{"type":"gain","label":"item","base_id":4000009,"bind":1,"num":2},{"type":"gain","label":"item","base_id":4000004,"bind":1,"num":1}]},"2":{"term_id":1,"num":5,"award":[{"type":"gain","label":"item","base_id":4000012,"bind":1,"num":2}],"award2":[{"type":"gain","label":"item","base_id":4000012,"bind":1,"num":5}]},"3":{"term_id":1,"num":10,"award":[{"type":"gain","label":"item","base_id":4000012,"bind":1,"num":2}],"award2":[{"type":"gain","label":"item","base_id":4000012,"bind":1,"num":5}]},"4":{"term_id":1,"num":20,"award":[{"type":"gain","label":"item","base_id":4000012,"bind":1,"num":2}],"award2":[{"type":"gain","label":"item","base_id":4000012,"bind":1,"num":5}]},"5":{"term_id":1,"num":30,"award":[{"type":"gain","label":"item","base_id":4000009,"bind":1,"num":1}],"award2":[{"type":"gain","label":"item","base_id":4000011,"bind":1,"num":1},{"type":"gain","label":"item","base_id":4000004,"bind":1,"num":1}]},"6":{"term_id":1,"num":45,"award":[{"type":"gain","label":"item","base_id":4000012,"bind":1,"num":2}],"award2":[{"type":"gain","label":"item","base_id":4000012,"bind":1,"num":5}]},"7":{"term_id":1,"num":60,"award":[{"type":"gain","label":"item","base_id":4000012,"bind":1,"num":2}],"award2":[{"type":"gain","label":"item","base_id":4000012,"bind":1,"num":5}]},"8":{"term_id":1,"num":80,"award":[{"type":"gain","label":"item","base_id":4000012,"bind":1,"num":2}],"award2":[{"type":"gain","label":"item","base_id":4000012,"bind":1,"num":5}]},"9":{"term_id":1,"num":100,"award":[{"type":"gain","label":"item","base_id":4000009,"bind":1,"num":1}],"award2":[{"type":"gain","label":"item","base_id":4000009,"bind":1,"num":2},{"type":"gain","label":"item","base_id":4000004,"bind":1,"num":1}]},"10":{"term_id":1,"num":125,"award":[{"type":"gain","label":"item","base_id":4000012,"bind":1,"num":2}],"award2":[{"type":"gain","label":"item","base_id":4000012,"bind":1,"num":5}]},"11":{"term_id":1,"num":150,"award":[{"type":"gain","label":"item","base_id":4000012,"bind":1,"num":2}],"award2":[{"type":"gain","label":"item","base_id":4000012,"bind":1,"num":5}]},"12":{"term_id":1,"num":175,"award":[{"type":"gain","label":"item","base_id":4000012,"bind":1,"num":2}],"award2":[{"type":"gain","label":"item","base_id":4000012,"bind":1,"num":5}]},"13":{"term_id":1,"num":200,"award":[{"type":"gain","label":"item","base_id":4000009,"bind":1,"num":1}],"award2":[{"type":"gain","label":"item","base_id":4000011,"bind":1,"num":1},{"type":"gain","label":"item","base_id":4000004,"bind":1,"num":1}]},"14":{"term_id":1,"num":225,"award":[{"type":"gain","label":"item","base_id":4000012,"bind":1,"num":2}],"award2":[{"type":"gain","label":"item","base_id":4000012,"bind":1,"num":5}]},"15":{"term_id":1,"num":250,"award":[{"type":"gain","label":"item","base_id":4000012,"bind":1,"num":2}],"award2":[{"type":"gain","label":"item","base_id":4000012,"bind":1,"num":5}]},"16":{"term_id":1,"num":275,"award":[{"type":"gain","label":"item","base_id":4000012,"bind":1,"num":2}],"award2":[{"type":"gain","label":"item","base_id":4000012,"bind":1,"num":5}]},"17":{"term_id":1,"num":300,"award":[{"type":"gain","label":"item","base_id":4000009,"bind":1,"num":1}],"award2":[{"type":"gain","label":"item","base_id":4000009,"bind":1,"num":2},{"type":"gain","label":"item","base_id":4000004,"bind":1,"num":1}]},"18":{"term_id":1,"num":325,"award":[{"type":"gain","label":"item","base_id":4000012,"bind":1,"num":2}],"award2":[{"type":"gain","label":"item","base_id":4000012,"bind":1,"num":5}]},"19":{"term_id":1,"num":350,"award":[{"type":"gain","label":"item","base_id":4000012,"bind":1,"num":2}],"award2":[{"type":"gain","label":"item","base_id":4000012,"bind":1,"num":5}]},"20":{"term_id":1,"num":375,"award":[{"type":"gain","label":"item","base_id":4000012,"bind":1,"num":2}],"award2":[{"type":"gain","label":"item","base_id":4000012,"bind":1,"num":5}]},"21":{"term_id":1,"num":400,"award":[{"type":"gain","label":"item","base_id":4000011,"bind":1,"num":1}],"award2":[{"type":"gain","label":"item","base_id":4000010,"bind":1,"num":1},{"type":"gain","label":"item","base_id":4000004,"bind":1,"num":1}]},"22":{"term_id":1,"num":425,"award":"","award2":[{"type":"gain","label":"item","base_id":4000012,"bind":1,"num":5}]},"23":{"term_id":1,"num":450,"award":"","award2":[{"type":"gain","label":"item","base_id":4000012,"bind":1,"num":5}]},"24":{"term_id":1,"num":475,"award":"","award2":[{"type":"gain","label":"item","base_id":4000012,"bind":1,"num":5}]},"25":{"term_id":1,"num":500,"award":"","award2":[{"type":"gain","label":"item","base_id":4000011,"bind":1,"num":1},{"type":"gain","label":"item","base_id":4000004,"bind":1,"num":1}]},"26":{"term_id":2,"num":1,"award":[{"type":"gain","label":"item","base_id":4000009,"bind":1,"num":1}],"award2":[{"type":"gain","label":"item","base_id":4000009,"bind":1,"num":2},{"type":"gain","label":"item","base_id":4000004,"bind":1,"num":1}]},"27":{"term_id":2,"num":5,"award":[{"type":"gain","label":"item","base_id":4000012,"bind":1,"num":2}],"award2":[{"type":"gain","label":"item","base_id":4000012,"bind":1,"num":5}]},"28":{"term_id":2,"num":10,"award":[{"type":"gain","label":"item","base_id":4000012,"bind":1,"num":2}],"award2":[{"type":"gain","label":"item","base_id":4000012,"bind":1,"num":5}]},"29":{"term_id":2,"num":20,"award":[{"type":"gain","label":"item","base_id":4000012,"bind":1,"num":2}],"award2":[{"type":"gain","label":"item","base_id":4000012,"bind":1,"num":5}]},"30":{"term_id":2,"num":30,"award":[{"type":"gain","label":"item","base_id":4000009,"bind":1,"num":1}],"award2":[{"type":"gain","label":"item","base_id":4000011,"bind":1,"num":1},{"type":"gain","label":"item","base_id":4000004,"bind":1,"num":1}]},"31":{"term_id":2,"num":45,"award":[{"type":"gain","label":"item","base_id":4000012,"bind":1,"num":2}],"award2":[{"type":"gain","label":"item","base_id":4000012,"bind":1,"num":5}]},"32":{"term_id":2,"num":60,"award":[{"type":"gain","label":"item","base_id":4000012,"bind":1,"num":2}],"award2":[{"type":"gain","label":"item","base_id":4000012,"bind":1,"num":5}]},"33":{"term_id":2,"num":80,"award":[{"type":"gain","label":"item","base_id":4000012,"bind":1,"num":2}],"award2":[{"type":"gain","label":"item","base_id":4000012,"bind":1,"num":5}]},"34":{"term_id":2,"num":100,"award":[{"type":"gain","label":"item","base_id":4000009,"bind":1,"num":1}],"award2":[{"type":"gain","label":"item","base_id":4000009,"bind":1,"num":2},{"type":"gain","label":"item","base_id":4000004,"bind":1,"num":1}]},"35":{"term_id":2,"num":125,"award":[{"type":"gain","label":"item","base_id":4000012,"bind":1,"num":2}],"award2":[{"type":"gain","label":"item","base_id":4000012,"bind":1,"num":5}]},"36":{"term_id":2,"num":150,"award":[{"type":"gain","label":"item","base_id":4000012,"bind":1,"num":2}],"award2":[{"type":"gain","label":"item","base_id":4000012,"bind":1,"num":5}]},"37":{"term_id":2,"num":175,"award":[{"type":"gain","label":"item","base_id":4000012,"bind":1,"num":2}],"award2":[{"type":"gain","label":"item","base_id":4000012,"bind":1,"num":5}]},"38":{"term_id":2,"num":200,"award":[{"type":"gain","label":"item","base_id":4000009,"bind":1,"num":1}],"award2":[{"type":"gain","label":"item","base_id":4000011,"bind":1,"num":1},{"type":"gain","label":"item","base_id":4000004,"bind":1,"num":1}]},"39":{"term_id":2,"num":225,"award":[{"type":"gain","label":"item","base_id":4000012,"bind":1,"num":2}],"award2":[{"type":"gain","label":"item","base_id":4000012,"bind":1,"num":5}]},"40":{"term_id":2,"num":250,"award":[{"type":"gain","label":"item","base_id":4000012,"bind":1,"num":2}],"award2":[{"type":"gain","label":"item","base_id":4000012,"bind":1,"num":5}]},"41":{"term_id":2,"num":275,"award":[{"type":"gain","label":"item","base_id":4000012,"bind":1,"num":2}],"award2":[{"type":"gain","label":"item","base_id":4000012,"bind":1,"num":5}]},"42":{"term_id":2,"num":300,"award":[{"type":"gain","label":"item","base_id":4000009,"bind":1,"num":1}],"award2":[{"type":"gain","label":"item","base_id":4000009,"bind":1,"num":2},{"type":"gain","label":"item","base_id":4000004,"bind":1,"num":1}]},"43":{"term_id":2,"num":325,"award":[{"type":"gain","label":"item","base_id":4000012,"bind":1,"num":2}],"award2":[{"type":"gain","label":"item","base_id":4000012,"bind":1,"num":5}]},"44":{"term_id":2,"num":350,"award":[{"type":"gain","label":"item","base_id":4000012,"bind":1,"num":2}],"award2":[{"type":"gain","label":"item","base_id":4000012,"bind":1,"num":5}]},"45":{"term_id":2,"num":375,"award":[{"type":"gain","label":"item","base_id":4000012,"bind":1,"num":2}],"award2":[{"type":"gain","label":"item","base_id":4000012,"bind":1,"num":5}]},"46":{"term_id":2,"num":400,"award":[{"type":"gain","label":"item","base_id":4000011,"bind":1,"num":1}],"award2":[{"type":"gain","label":"item","base_id":4000010,"bind":1,"num":1},{"type":"gain","label":"item","base_id":4000004,"bind":1,"num":1}]},"47":{"term_id":2,"num":425,"award":"","award2":[{"type":"gain","label":"item","base_id":4000012,"bind":1,"num":5}]},"48":{"term_id":2,"num":450,"award":"","award2":[{"type":"gain","label":"item","base_id":4000012,"bind":1,"num":5}]},"49":{"term_id":2,"num":475,"award":"","award2":[{"type":"gain","label":"item","base_id":4000012,"bind":1,"num":5}]},"50":{"term_id":2,"num":500,"award":"","award2":[{"type":"gain","label":"item","base_id":4000011,"bind":1,"num":1},{"type":"gain","label":"item","base_id":4000004,"bind":1,"num":1}]},"51":{"term_id":3,"num":1,"award":[{"type":"gain","label":"item","base_id":4000009,"bind":1,"num":1}],"award2":[{"type":"gain","label":"item","base_id":4000009,"bind":1,"num":2},{"type":"gain","label":"item","base_id":4000004,"bind":1,"num":1}]},"52":{"term_id":3,"num":5,"award":[{"type":"gain","label":"item","base_id":4000012,"bind":1,"num":2}],"award2":[{"type":"gain","label":"item","base_id":4000012,"bind":1,"num":5}]},"53":{"term_id":3,"num":10,"award":[{"type":"gain","label":"item","base_id":4000012,"bind":1,"num":2}],"award2":[{"type":"gain","label":"item","base_id":4000012,"bind":1,"num":5}]},"54":{"term_id":3,"num":20,"award":[{"type":"gain","label":"item","base_id":4000012,"bind":1,"num":2}],"award2":[{"type":"gain","label":"item","base_id":4000012,"bind":1,"num":5}]},"55":{"term_id":3,"num":30,"award":[{"type":"gain","label":"item","base_id":4000009,"bind":1,"num":1}],"award2":[{"type":"gain","label":"item","base_id":4000011,"bind":1,"num":1},{"type":"gain","label":"item","base_id":4000004,"bind":1,"num":1}]},"56":{"term_id":3,"num":45,"award":[{"type":"gain","label":"item","base_id":4000012,"bind":1,"num":2}],"award2":[{"type":"gain","label":"item","base_id":4000012,"bind":1,"num":5}]},"57":{"term_id":3,"num":60,"award":[{"type":"gain","label":"item","base_id":4000012,"bind":1,"num":2}],"award2":[{"type":"gain","label":"item","base_id":4000012,"bind":1,"num":5}]},"58":{"term_id":3,"num":80,"award":[{"type":"gain","label":"item","base_id":4000012,"bind":1,"num":2}],"award2":[{"type":"gain","label":"item","base_id":4000012,"bind":1,"num":5}]},"59":{"term_id":3,"num":100,"award":[{"type":"gain","label":"item","base_id":4000009,"bind":1,"num":1}],"award2":[{"type":"gain","label":"item","base_id":4000009,"bind":1,"num":2},{"type":"gain","label":"item","base_id":4000004,"bind":1,"num":1}]},"60":{"term_id":3,"num":125,"award":[{"type":"gain","label":"item","base_id":4000012,"bind":1,"num":2}],"award2":[{"type":"gain","label":"item","base_id":4000012,"bind":1,"num":5}]},"61":{"term_id":3,"num":150,"award":[{"type":"gain","label":"item","base_id":4000012,"bind":1,"num":2}],"award2":[{"type":"gain","label":"item","base_id":4000012,"bind":1,"num":5}]},"62":{"term_id":3,"num":175,"award":[{"type":"gain","label":"item","base_id":4000012,"bind":1,"num":2}],"award2":[{"type":"gain","label":"item","base_id":4000012,"bind":1,"num":5}]},"63":{"term_id":3,"num":200,"award":[{"type":"gain","label":"item","base_id":4000009,"bind":1,"num":1}],"award2":[{"type":"gain","label":"item","base_id":4000011,"bind":1,"num":1},{"type":"gain","label":"item","base_id":4000004,"bind":1,"num":1}]},"64":{"term_id":3,"num":225,"award":[{"type":"gain","label":"item","base_id":4000012,"bind":1,"num":2}],"award2":[{"type":"gain","label":"item","base_id":4000012,"bind":1,"num":5}]},"65":{"term_id":3,"num":250,"award":[{"type":"gain","label":"item","base_id":4000012,"bind":1,"num":2}],"award2":[{"type":"gain","label":"item","base_id":4000012,"bind":1,"num":5}]},"66":{"term_id":3,"num":275,"award":[{"type":"gain","label":"item","base_id":4000012,"bind":1,"num":2}],"award2":[{"type":"gain","label":"item","base_id":4000012,"bind":1,"num":5}]},"67":{"term_id":3,"num":300,"award":[{"type":"gain","label":"item","base_id":4000009,"bind":1,"num":1}],"award2":[{"type":"gain","label":"item","base_id":4000009,"bind":1,"num":2},{"type":"gain","label":"item","base_id":4000004,"bind":1,"num":1}]},"68":{"term_id":3,"num":325,"award":[{"type":"gain","label":"item","base_id":4000012,"bind":1,"num":2}],"award2":[{"type":"gain","label":"item","base_id":4000012,"bind":1,"num":5}]},"69":{"term_id":3,"num":350,"award":[{"type":"gain","label":"item","base_id":4000012,"bind":1,"num":2}],"award2":[{"type":"gain","label":"item","base_id":4000012,"bind":1,"num":5}]},"70":{"term_id":3,"num":375,"award":[{"type":"gain","label":"item","base_id":4000012,"bind":1,"num":2}],"award2":[{"type":"gain","label":"item","base_id":4000012,"bind":1,"num":5}]},"71":{"term_id":3,"num":400,"award":[{"type":"gain","label":"item","base_id":4000011,"bind":1,"num":1}],"award2":[{"type":"gain","label":"item","base_id":4000010,"bind":1,"num":1},{"type":"gain","label":"item","base_id":4000004,"bind":1,"num":1}]},"72":{"term_id":3,"num":425,"award":"","award2":[{"type":"gain","label":"item","base_id":4000012,"bind":1,"num":5}]},"73":{"term_id":3,"num":450,"award":"","award2":[{"type":"gain","label":"item","base_id":4000012,"bind":1,"num":5}]},"74":{"term_id":3,"num":475,"award":"","award2":[{"type":"gain","label":"item","base_id":4000012,"bind":1,"num":5}]},"75":{"term_id":3,"num":500,"award":"","award2":[{"type":"gain","label":"item","base_id":4000011,"bind":1,"num":1},{"type":"gain","label":"item","base_id":4000004,"bind":1,"num":1}]}}}